rebrick/Core.py
rebrick/DriveTrain.py
rebrick/Math.py
rebrick/Physics.py
rebrick/Physics1D.py
rebrick/Physics3D.py
rebrick/Robotics.py
rebrick/Simulation.py
rebrick/Terrain.py
rebrick/Urdf.py
rebrick/Vehicles.py
rebrick/Visuals.py
rebrick/_BrickAgxPyApi.cpython-310-x86_64-linux-gnu.so
rebrick/_CorePythonSwig.cpython-310-x86_64-linux-gnu.so
rebrick/_DriveTrainSwig.cpython-310-x86_64-linux-gnu.so
rebrick/_MathSwig.cpython-310-x86_64-linux-gnu.so
rebrick/_Physics1DSwig.cpython-310-x86_64-linux-gnu.so
rebrick/_Physics3DSwig.cpython-310-x86_64-linux-gnu.so
rebrick/_PhysicsSwig.cpython-310-x86_64-linux-gnu.so
rebrick/_RoboticsSwig.cpython-310-x86_64-linux-gnu.so
rebrick/_SimulationSwig.cpython-310-x86_64-linux-gnu.so
rebrick/_TerrainSwig.cpython-310-x86_64-linux-gnu.so
rebrick/_UrdfSwig.cpython-310-x86_64-linux-gnu.so
rebrick/_VehiclesSwig.cpython-310-x86_64-linux-gnu.so
rebrick/_VisualsSwig.cpython-310-x86_64-linux-gnu.so
rebrick/__init__.py
rebrick/agxtobrick.py
rebrick/anytobrick.py
rebrick/api.py
rebrick/brickapplication.py
rebrick/brickserialize.py
rebrick/brickvalidate.py
rebrick/brickview.py
rebrick/migrate.py
rebrick/migration_hint.py
rebrick/migrations.py
rebrick/versionaction.py
brickagx-0.14.0.dist-info/METADATA
brickagx-0.14.0.dist-info/WHEEL
brickagx-0.14.0.dist-info/entry_points.txt
brickagx-0.14.0.dist-info/RECORD
