Metadata-Version: 2.1
Name: BrickAgx
Version: 0.14.0
Summary: Brick.AGX python interface development
Home-page: https://pub.algoryx.dev/brick/
License: Apache 2.0
Author: Algoryx
Author-email: algoryx@algoryx.com
Requires-Python: >=3.8
Classifier: Intended Audience :: Manufacturing
Classifier: Intended Audience :: Science/Research
Classifier: License :: Other/Proprietary License
Classifier: Programming Language :: Python :: 3
Classifier: Programming Language :: Python :: 3.8
Classifier: Programming Language :: Python :: 3.9
Classifier: Programming Language :: Python :: 3.10
Classifier: Programming Language :: Python :: 3.11
Classifier: Programming Language :: Python :: 3.12
Classifier: Topic :: Scientific/Engineering :: Physics
Classifier: Topic :: Scientific/Engineering :: Visualization
Requires-Dist: agx (==2.38.0.2)
Requires-Dist: brickbundles (>=0.14.0,<0.15.0)
Requires-Dist: pclick (>=0.4.1,<0.5.0)
